dcspray/__init_.py
dcspray/cli.py
dcspray/util/__init__.py
dcspray/util/auth.py
dcspray/util/branding.py
dcspray/util/models.py
dcspray-1.0.0.dist-info/entry_points.txt
dcspray-1.0.0.dist-info/LICENSE
dcspray-1.0.0.dist-info/WHEEL
dcspray-1.0.0.dist-info/METADATA
dcspray-1.0.0.dist-info/RECORD
